mujoco_utils/__init__.py
mujoco_utils/collision_utils.py
mujoco_utils/composer_utils.py
mujoco_utils/composer_utils_test.py
mujoco_utils/mjcf_utils.py
mujoco_utils/noise_utils.py
mujoco_utils/physics_utils.py
mujoco_utils/py.typed
mujoco_utils/spec_utils.py
mujoco_utils/types.py
mujoco_utils-0.0.6.dist-info/LICENSE
mujoco_utils-0.0.6.dist-info/METADATA
mujoco_utils-0.0.6.dist-info/WHEEL
mujoco_utils-0.0.6.dist-info/top_level.txt
mujoco_utils-0.0.6.dist-info/RECORD
